LICENSE
MANIFEST.in
README.md
VERSION
requirements.txt
setup.cfg
setup.py
rhasspy_nlu.egg-info/PKG-INFO
rhasspy_nlu.egg-info/SOURCES.txt
rhasspy_nlu.egg-info/dependency_links.txt
rhasspy_nlu.egg-info/requires.txt
rhasspy_nlu.egg-info/top_level.txt
rhasspynlu/__init__.py
rhasspynlu/__main__.py
rhasspynlu/arpa_lm.py
rhasspynlu/const.py
rhasspynlu/evaluate.py
rhasspynlu/fsticuffs.py
rhasspynlu/g2p.py
rhasspynlu/g2p_geepers.py
rhasspynlu/ini_jsgf.py
rhasspynlu/intent.py
rhasspynlu/jsgf.py
rhasspynlu/jsgf_graph.py
rhasspynlu/ngram.py
rhasspynlu/numbers.py
rhasspynlu/py.typed
rhasspynlu/slots.py
rhasspynlu/utils.py
tests/__init__.py
tests/test_evaluate.py
tests/test_fsticuffs.py
tests/test_g2p.py
tests/test_ini_jsgf.py
tests/test_jsgf.py
tests/test_jsgf_graph.py